mcp_mobile_app/__init__.py
mcp_mobile_app/server.py
mcp_mobile_app-0.1.1.dist-info/METADATA
mcp_mobile_app-0.1.1.dist-info/WHEEL
mcp_mobile_app-0.1.1.dist-info/entry_points.txt
mcp_mobile_app-0.1.1.dist-info/RECORD
