Metadata-Version: 2.4
Name: mcp-mobile-app
Version: 0.1.1
Summary: MCP Server for Mobile App Development - Generate Login, Home, and Settings pages for React Native, Flutter, SwiftUI, and Kotlin
Project-URL: Homepage, https://github.com/MVVKUR/mcp-mobile-app
Project-URL: Repository, https://github.com/MVVKUR/mcp-mobile-app
Author: MVVKUR
License-Expression: MIT
Keywords: ai,claude,copilot,flutter,kotlin,mcp,mobile,react-native,swiftui
Classifier: Development Status :: 4 - Beta
Classifier: Intended Audience :: Developers
Classifier: License :: OSI Approved :: MIT License
Classifier: Programming Language :: Python :: 3
Classifier: Programming Language :: Python :: 3.10
Classifier: Programming Language :: Python :: 3.11
Classifier: Programming Language :: Python :: 3.12
Requires-Python: >=3.10
Requires-Dist: mcp>=1.0.0
